Workbook

Sheet Catalogo
A1: Catálogo de métricas de calidad — Sembrando Futuro (documento 23)
A3: ID | B3: Familia | C3: Métrica y fórmula | D3: Meta | E3: Herramienta o fuente | F3: Cuándo | G3: Quién
A4: M-01 | B4: Producto | C4: Cumplimiento de requisitos funcionales = RF verificados ÷ 19 × 100 | D4: 100 % | E4: Hoja Plan_Pruebas (documento 14) | F4: Fin de cada sprint | G4: M y K
A5: M-02 | B5: Producto | C5: Cumplimiento de requisitos no funcionales = RNF verificados ÷ 12 × 100 | D5: 100 % | E5: Hoja RNF (documento 14) | F5: Sprint 4 | G5: M y K
A6: M-03 | B6: Producto | C6: Exactitud del cálculo = |valor obtenido − valor esperado| ÷ valor esperado × 100 | D6: ≤ 0,0001 % (RNF-22) | E6: Pruebas unitarias con los valores del documento 19 | F6: Cada cambio de fórmula | G6: K
A7: M-04 | B7: Producto | C7: Tiempo de respuesta de los cálculos (matas, costos y utilidad) | D7: ≤ 2,0 s en el 95 % de las pruebas (RNF-01) | E7: performance.now en un equipo de 2 GB de RAM | F7: Sprints 2 y 4 | G7: K
A8: M-05 | B8: Producto | C8: Accesibilidad visual de todas las pantallas | D8: WCAG 2.1 AA (RNF-07) y puntaje de accesibilidad de Lighthouse de 90 o más | E8: Lighthouse y revisión de contraste | F8: Sprints 2, 3 y 4 | G8: K
A9: M-06 | B9: Producto | C9: Éxito de usabilidad = tareas terminadas sin ayuda ÷ tareas intentadas × 100 | D9: ≥ 90 % con al menos 5 agricultores (RNF-05) | E9: Prueba de usabilidad | F9: Sprint 4 | G9: K
A10: M-07 | B10: Producto | C10: Vulnerabilidades abiertas de severidad alta o media (inyección SQL y XSS) y tráfico sin cifrar | D10: 0 vulnerabilidades y 100 % del tráfico con HTTPS (TLS 1.2 o superior) (RNF-09, RNF-14) | E10: OWASP ZAP y SSL Labs | F10: Sprints 1 y 4 | G10: M
A11: M-08 | B11: Producto | C11: Disponibilidad del servidor = (minutos del mes − minutos sin servicio) ÷ minutos del mes × 100 | D11: ≥ 99,0 %, es decir, hasta 7,2 h sin servicio al mes (RNF-10) | E11: Monitoreo del servicio de producción | F11: Cada mes en producción | G11: M
A12: M-09 | B12: Pruebas | C12: Ejecución del plan = casos ejecutados ÷ casos definidos × 100 (229 de caja negra y 28 de caja blanca) | D12: 100 % al cierre | E12: Documentos 14 y 22 | F12: Fin de cada sprint | G12: M y K
A13: M-10 | B13: Pruebas | C13: Casos aprobados = casos aprobados ÷ casos ejecutados × 100 | D13: ≥ 95 % y cero defectos abiertos de severidad bloqueante, alta o media | E13: Documentos 14 y 22 | F13: Fin de cada sprint | G13: M y K
A14: M-11 | B14: Pruebas | C14: Trazabilidad = requisitos funcionales con al menos un caso de prueba ÷ 19 × 100 | D14: 100 % | E14: Matriz de trazabilidad (documento 14) | F14: Sprint 0 y en cada cambio | G14: K
... A28: M-25 | B28: Proceso | C28: Revisión formal = puntos cumplidos del acta ÷ 17 × 100 | D28: 100 % al cerrar los sprints 0 y 4 | E28: Acta de revisión (documento 16) | F28: Sprints 0 y 4 | G28: M y K

Sheet Mediciones
A1: Mediciones automáticas — 28 de octubre de 2026 (entorno de desarrollo)
A2: Solo lo que se pudo medir con pruebas y herramientas. Las métricas de tiempo, personas y servidor publicado quedan vacías: son datos reales del equipo (bitácoras PSP, acta, monitoreo).
A3: ID | B3: Métrica | C3: Meta | D3: Valor medido | E3: ¿Cumple? | F3: Cómo se midió | G3: Limitación u observación
A4: M-01 | B4: Cumplimiento de requisitos funcionales = RF verificados ÷ 19 × 100 | C4: Cumplimiento de requisitos funcionales = RF verificados ÷ 19 × 100 | D4: 19 de 19 RF verificados (100 %) | E4: Sí | F4: Hoja Plan_Pruebas del documento 14: un requisito cuenta si todos sus casos están «Aprobado» | G4: Los 19 RF tienen todos sus casos aprobados. Los casos de formato y de navegador se ejecutaron en Chromium; falta repetirlos en los teléfonos reales.
A5: M-02 | B5: Cumplimiento de requisitos no funcionales = RNF verificados ÷ 12 × 100 | C5: Cumplimiento de requisitos no funcionales = RNF verificados ÷ 12 × 100 | D5: 6 de 12 RNF verificados (50 %) | E5: No | F5: Hoja Plan_Pruebas: RNF-11, 15, 16, 17, 22 y 25 aprobados | G5: Los otros 6 (RNF-01, 05, 07, 09, 10 y 14) quedan «Pendiente» porque piden una herramienta o a personas: equipo de 2 GB, 5 agricultores, Lighthouse, OWASP ZAP, monitoreo mensual y SSL Labs.
A6: M-03 | B6: Exactitud del cálculo = |valor obtenido − valor esperado| ÷ valor esperado × 100 | C6: Exactitud del cálculo = |valor obtenido − valor esperado| ÷ valor esperado × 100 | D6: 0,000094 % de error relativo máximo (7 cálculos) | E6: Sí | F6: Prueba test_CP_RNF_22 contra los valores oráculo del plan | G6: El mayor error es el del tresbolillo: el servidor redondea a 2 decimales (1.283,00 frente a 1.283,0012).
A7: M-04 | B7: Tiempo de respuesta de los cálculos (matas, costos y utilidad) | C7: Tiempo de respuesta de los cálculos (matas, costos y utilidad) | D7: p95 = 3 ms y máximo = 4 ms en 20 cálculos | E7: Sí, solo en desarrollo | F7: performance.now() en Chromium sin pantalla con el procesador 4 veces más lento (e2e_plan.cjs) | G7: No es el equipo de 2 GB de RAM de la meta: falta repetirlo en un teléfono real.
A8: M-05 | B8: Accesibilidad visual de todas las pantallas | C8: Accesibilidad visual de todas las pantallas | D8: 0 textos menores de 16 px, 0 controles menores de 48 × 48 px y 0 contrastes menores de 4,5:1 en 7 pantallas; 29 etiquetas de 16 px (navegación, indicadores, marcos) | E8: Parcial | F8: Medición con JavaScript en el navegador (e2e_plan.cjs) | G8: Faltan el puntaje de Lighthouse (90 o más) y la revisión manual de WCAG 2.1 AA.
A9: M-06 | B9: Éxito de usabilidad = tareas terminadas sin ayuda ÷ tareas intentadas × 100 | C9: Éxito de usabilidad = tareas terminadas sin ayuda ÷ tareas intentadas × 100 | F9: Prueba con al menos 5 agricultores | G9: Dato del equipo: se llena después de la prueba con personas.
A10: M-07 | B10: Vulnerabilidades abiertas de severidad alta o media (inyección SQL y XSS) y tráfico sin cifrar | C10: Vulnerabilidades abiertas de severidad alta o media (inyección SQL y XSS) y tráfico sin cifrar | D10: 0 consultas con datos del usuario escritas a mano (todo pasa por el ORM); inyección de código rechazada en formularios y servidor | E10: Parcial | F10: Revisión del código y pruebas CP-RNF-09 y CP-RNF-14 | G10: Faltan OWASP ZAP y SSL Labs, que se ejecutan contra el sitio publicado.
A11: M-08 | B11: Disponibilidad del servidor = (minutos del mes − minutos sin servicio) ÷ minutos del mes × 100 | C11: Disponibilidad del servidor = (minutos del mes − minutos sin servicio) ÷ minutos del mes × 100 | F11: Monitoreo del servicio publicado | G11: Dato del equipo: se mide durante un mes con el servidor en Render.
A12: M-09 | B12: Ejecución del plan = casos ejecutados ÷ casos definidos × 100 (229 de caja negra y 28 de caja blanca) | C12: Ejecución del plan = casos ejecutados ÷ casos definidos × 100 (229 de caja negra y 28 de caja blanca) | D12: 247 de 257 casos ejecutados (96,1 %): 219 de 229 de caja negra y 28 de 28 de caja blanca | E12: No | F12: Documentos 14 y 22 (scripts/rellenar_plan.py) | G12: Los 10 casos pendientes necesitan herramientas o personas (ver M-02 y las bitácoras PSP).
A13: M-10 | B13: Casos aprobados = casos aprobados ÷ casos ejecutados × 100 | C13: Casos aprobados = casos aprobados ÷ casos ejecutados × 100 | D13: 247 aprobados de 247 ejecutados (100 %); 0 fallidos | E13: Sí | F13: Documentos 14 y 22 | G13: Se hallaron y corrigieron 5 defectos durante la ejecución (hoja Registro_Defectos); ninguno queda abierto.
A14: M-11 | B14: Trazabilidad = requisitos funcionales con al menos un caso de prueba ÷ 19 × 100 | C14: Trazabilidad = requisitos funcionales con al menos un caso de prueba ÷ 19 × 100 | D14: 19 de 19 RF con al menos un caso (100 %) | E14: Sí | F14: Matriz de trazabilidad del documento 14
A15: M-12 | B15: Densidad de defectos encontrados = defectos registrados en el sprint ÷ KLOC (miles de líneas de código sin comentarios) | C15: Densidad de defectos encontrados = defectos registrados en el sprint ÷ KLOC (miles de líneas de código sin comentarios) | D15: 5 defectos ÷ 3,8 KLOC = 1,3 por KLOC | E15: Informativa | F15: Hoja Registro_Defectos y conteo de líneas (2.383 de servidor y 1.449 de dispositivo, sin comentarios ni líneas vacías) | G15: Es la primera medición: sirve de base para comparar con el siguiente sprint.
A16: M-13 | B16: Densidad de defectos residuales = defectos abiertos al cierre, de cualquier severidad, ÷ KLOC | C16: Densidad de defectos residuales = defectos abiertos al cierre, de cualquier severidad, ÷ KLOC | D16: 0 defectos abiertos ÷ 3,8 KLOC = 0 por KLOC | E16: Sí | F16: Hoja Registro_Defectos | G16: Cuenta los defectos hallados con este plan; si aparecen más en la sustentación, hay que registrarlos.
A17: M-14 | B17: Defectos por requisito = defectos del requisito ÷ casos de prueba del requisito | C17: Defectos por requisito = defectos del requisito ÷ casos de prueba del requisito | D17: Informativa: RF-13, RF-28, RF-04 y RNF-07 tuvieron 1 defecto cada uno; los demás 0 | E17: Informativa | F17: Hoja Registro_Defectos y casos del plan
A18: M-15 | B18: Cobertura de sentencias = instrucciones ejecutadas por las pruebas ÷ instrucciones totales × 100 | C18: Cobertura de sentencias = instrucciones ejecutadas por las pruebas ÷ instrucciones totales × 100 | D18: Servidor: 96,8 % de líneas (2.183 de 2.256). Dispositivo: 100 % de líneas en los módulos de cálculo (formulas.js, validaciones.js, formato.js). | E18: Sí | F18: Servidor: medición propia con sys.monitoring; dispositivo: node --test --experimental-test-coverage | G18: Aproximada: pytest-cov no está instalado en el entorno de desarrollo; el número oficial sale de la integración continua.
A19: M-16 | B19: Cobertura de ramas = salidas de decisiones ejecutadas ÷ salidas totales × 100 | C19: Cobertura de ramas = salidas de decisiones ejecutadas ÷ salidas totales × 100 | D19: Servidor: 85,0 % de ramas (860 de 1.012). domain/validaciones.py 89,1 %; acceso.py 91,2 %; formulas.py 97,6 %. Dispositivo: 92,2 % de ramas. | E19: Sí | F19: Servidor: medición propia con eventos de ramas de sys.monitoring; dispositivo: node:test | G19: Aproximada (cuenta cada operando de las condiciones compuestas). El 100 % de decisiones de las 4 funciones se logra por diseño con los 28 casos CB-xx, que pasan.
A20: M-17 | B20: Complejidad ciclomática de cada función (caminos independientes) | C20: Complejidad ciclomática de cada función (caminos independientes) | D20: Servidor: máximo 9 (iniciar_sesion y _validar_ciclo_cultivo). Dispositivo: ninguna función pasa de 10. | E20: Sí | F20: Servidor: conteo de if, for, while y except con ast; dispositivo: cc.mjs con acorn (regla de ESLint equivalente) | G20: Aproximada: flake8, ESLint y SonarQube no se pudieron instalar en el entorno de desarrollo.
A21: M-18 | B21: Duplicación = líneas repetidas ÷ líneas totales × 100 | C21: Duplicación = líneas repetidas ÷ líneas totales × 100 | F21: SonarCloud en la integración continua | G21: Aún no se mide: requiere SONAR_TOKEN y la organización.
A22: M-19 | B22: Errores de estilo del código | C22: Errores de estilo del código | F22: flake8 y ESLint en la integración continua | G22: Aún no se mide: las herramientas no se pudieron instalar en el entorno de desarrollo (sin red). Se revisaron a mano los imports sin usar, el largo de línea y la complejidad.
A23: M-20 | B23: Tasa de defectos por hora = defectos que introdujo la persona ÷ horas netas de diseño y programación | C23: Tasa de defectos por hora = defectos que introdujo la persona ÷ horas netas de diseño y programación | F23: Bitácora de tiempos (PSP), registro de defectos, cronograma y acta de revisión | G23: Dato del equipo: se llena durante los sprints. No se inventan tiempos.
A24: M-21 | B24: Defectos hallados por hora de revisión = defectos encontrados en revisiones ÷ horas de revisión | C24: Defectos hallados por hora de revisión = defectos encontrados en revisiones ÷ horas de revisión | F24: Bitácora de tiempos (PSP), registro de defectos, cronograma y acta de revisión | G24: Dato del equipo: se llena durante los sprints. No se inventan tiempos.
A25: M-22 | B25: Desviación del esfuerzo = (horas reales − horas estimadas) ÷ horas estimadas × 100 | C25: Desviación del esfuerzo = (horas reales − horas estimadas) ÷ horas estimadas × 100 | F25: Bitácora de tiempos (PSP), registro de defectos, cronograma y acta de revisión | G25: Dato del equipo: se llena durante los sprints. No se inventan tiempos.
A26: M-23 | B26: Cumplimiento del cronograma = tareas terminadas a tiempo ÷ tareas planeadas del sprint × 100 | C26: Cumplimiento del cronograma = tareas terminadas a tiempo ÷ tareas planeadas del sprint × 100 | F26: Bitácora de tiempos (PSP), registro de defectos, cronograma y acta de revisión | G26: Dato del equipo: se llena durante los sprints. No se inventan tiempos.
A27: M-24 | B27: Tiempo de corrección = horas entre el registro del defecto y su estado Verificado | C27: Tiempo de corrección = horas entre el registro del defecto y su estado Verificado | F27: Bitácora de tiempos (PSP), registro de defectos, cronograma y acta de revisión | G27: Dato del equipo: se llena durante los sprints. No se inventan tiempos.
A28: M-25 | B28: Revisión formal = puntos cumplidos del acta ÷ 17 × 100 | C28: Revisión formal = puntos cumplidos del acta ÷ 17 × 100 | F28: Bitácora de tiempos (PSP), registro de defectos, cronograma y acta de revisión | G28: Dato del equipo: se llena durante los sprints. No se inventan tiempos.

Sheet Bitacora_Tiempo
A1: Bitácora de tiempos (PSP). Anote cada bloque de trabajo; el tiempo neto se calcula solo.
A3: Fecha | B3: Sprint | C3: Integrante | D3: Actividad | E3: Inicio | F3: Fin | G3: Interrupción (min) | H3: Tiempo neto (min)
H4: =IF(OR(E4="",F4=""),"",ROUND((F4-E4)*1440-N(G4),0))
H5: =IF(OR(E5="",F5=""),"",ROUND((F5-E5)*1440-N(G5),0))
H6: =IF(OR(E6="",F6=""),"",ROUND((F6-E6)*1440-N(G6),0))
H7: =IF(OR(E7="",F7=""),"",ROUND((F7-E7)*1440-N(G7),0))
H8: =IF(OR(E8="",F8=""),"",ROUND((F8-E8)*1440-N(G8),0))
H9: =IF(OR(E9="",F9=""),"",ROUND((F9-E9)*1440-N(G9),0))
H10: =IF(OR(E10="",F10=""),"",ROUND((F10-E10)*1440-N(G10),0))
H11: =IF(OR(E11="",F11=""),"",ROUND((F11-E11)*1440-N(G11),0))
H12: =IF(OR(E12="",F12=""),"",ROUND((F12-E12)*1440-N(G12),0))
H13: =IF(OR(E13="",F13=""),"",ROUND((F13-E13)*1440-N(G13),0))
H14: =IF(OR(E14="",F14=""),"",ROUND((F14-E14)*1440-N(G14),0))
H15: =IF(OR(E15="",F15=""),"",ROUND((F15-E15)*1440-N(G15),0))
... H203: =IF(OR(E203="",F203=""),"",ROUND((F203-E203)*1440-N(G203),0))

Sheet Registro_Defectos
A1: Registro de defectos. Un defecto por fila; el identificador sigue el formato DEF-001.
A3: ID | B3: Fecha | C3: Sprint | D3: Caso que lo encontró | E3: Requisito | F3: Severidad | G3: Tipo | H3: Fase donde nació | I3: Fase donde se halló | J3: Horas de corrección | K3: Quién lo introdujo | L3: Estado | M3: Descripción y corrección
A4: DEF-01 | B4: 2026-10-28 | D4: CP-RF-13-02 | E4: RF-13 | F4: Media | G4: datos | H4: Diseño | I4: Pruebas | L4: Verificado | M4: La restricción CHECK de la base comparaba decimales como números flotantes y rechazaba un área no sembrable válida (0,9999 ha de 1,0 ha). Se cambió por una tolerancia de media diezmilésima (modelo y migración) y se verificó de punta a punta.
A5: DEF-02 | B5: 2026-10-28 | D5: CP-RF-28-04 | E5: RF-28 | F5: Media | G5: interfaz | H5: Código | I5: Pruebas | L5: Verificado | M5: Cuando los gastos superan los ingresos la pantalla decía «Utilidad neta» con una cifra negativa, sin la palabra «Pérdida» ni color rojo. Ahora muestra «Pérdida» en rojo (la palabra evita depender solo del color).
A6: DEF-03 | B6: 2026-10-28 | D6: CP-RF-28-08 | E6: RF-28 | F6: Baja | G6: interfaz | H6: Código | I6: Pruebas | L6: Verificado | M6: Los costos de la ficha técnica no avisaban que son orientativos. Se agregó «Son valores orientativos de la ficha técnica, no un presupuesto.»
A7: DEF-04 | B7: 2026-10-28 | D7: CP-RNF-07 | E7: RNF-07 | F7: Media | G7: interfaz | H7: Código | I7: Pruebas | L7: Verificado | M7: Había textos de 14 a 17 px y controles de 32 a 46 px de alto (indicador de conexión, botones de insignia, enlace de política) frente a los 18 px y 48 px del plan. Se subió el tamaño a 18 px (ayudas, avisos y etiquetas) y a 48 px mínimo en los controles; navegación, indicadores y marcos quedan en 16 px.
A8: DEF-05 | B8: 2026-10-28 | D8: CP-RF-04-01 | E8: RF-04 | F8: Baja | G8: interfaz | H8: Código | I8: Pruebas | L8: Verificado | M8: Si la persona tocaba «Cancelar» en la pregunta de cerrar sesión (o de cerrar el ciclo) y volvía a la pantalla, la pregunta seguía abierta. Ahora cada cambio de pantalla la reinicia.

Sheet Resumen_Sprint
A1: Informe de métricas por sprint. Escriba solo las celdas con borde grueso; el resto se calcula con fórmulas.
A3: Sprint | B3: Horas netas | C3: Defectos registrados | D3: Defectos por hora (M-20) | E3: Bloqueantes | F3: Altas | G3: Medias | H3: Bajas | I3: Horas estimadas | J3: Desviación del esfuerzo % (M-22) | K3: Tareas planeadas | L3: Tareas a tiempo | M3: Cumplimiento % (M-23)
A4: 0 | B4: =ROUND(SUMIFS(Bitacora_Tiempo!$H$4:$H$203,Bitacora_Tiempo!$B$4:$B$203,A4)/60,2) | C4: =COUNTIFS(Registro_Defectos!$C$4:$C$203,A4,Registro_Defectos!$A$4:$A$203,"<>") | D4: =IF(B4=0,"",ROUND(C4/B4,2)) | E4: =COUNTIFS(Registro_Defectos!$C$4:$C$203,A4,Registro_Defectos!$F$4:$F$203,"Bloqueante") | F4: =COUNTIFS(Registro_Defectos!$C$4:$C$203,A4,Registro_Defectos!$F$4:$F$203,"Alta") | G4: =COUNTIFS(Registro_Defectos!$C$4:$C$203,A4,Registro_Defectos!$F$4:$F$203,"Media") | H4: =COUNTIFS(Registro_Defectos!$C$4:$C$203,A4,Registro_Defectos!$F$4:$F$203,"Baja") | J4: =IF(OR(I4="",I4=0),"",ROUND((B4-I4)/I4*100,1)) | M4: =IF(OR(K4="",K4=0),"",ROUND(L4/K4*100,1))
A5: 1 | B5: =ROUND(SUMIFS(Bitacora_Tiempo!$H$4:$H$203,Bitacora_Tiempo!$B$4:$B$203,A5)/60,2) | C5: =COUNTIFS(Registro_Defectos!$C$4:$C$203,A5,Registro_Defectos!$A$4:$A$203,"<>") | D5: =IF(B5=0,"",ROUND(C5/B5,2)) | E5: =COUNTIFS(Registro_Defectos!$C$4:$C$203,A5,Registro_Defectos!$F$4:$F$203,"Bloqueante") | F5: =COUNTIFS(Registro_Defectos!$C$4:$C$203,A5,Registro_Defectos!$F$4:$F$203,"Alta") | G5: =COUNTIFS(Registro_Defectos!$C$4:$C$203,A5,Registro_Defectos!$F$4:$F$203,"Media") | H5: =COUNTIFS(Registro_Defectos!$C$4:$C$203,A5,Registro_Defectos!$F$4:$F$203,"Baja") | J5: =IF(OR(I5="",I5=0),"",ROUND((B5-I5)/I5*100,1)) | M5: =IF(OR(K5="",K5=0),"",ROUND(L5/K5*100,1))
A6: 2 | B6: =ROUND(SUMIFS(Bitacora_Tiempo!$H$4:$H$203,Bitacora_Tiempo!$B$4:$B$203,A6)/60,2) | C6: =COUNTIFS(Registro_Defectos!$C$4:$C$203,A6,Registro_Defectos!$A$4:$A$203,"<>") | D6: =IF(B6=0,"",ROUND(C6/B6,2)) | E6: =COUNTIFS(Registro_Defectos!$C$4:$C$203,A6,Registro_Defectos!$F$4:$F$203,"Bloqueante") | F6: =COUNTIFS(Registro_Defectos!$C$4:$C$203,A6,Registro_Defectos!$F$4:$F$203,"Alta") | G6: =COUNTIFS(Registro_Defectos!$C$4:$C$203,A6,Registro_Defectos!$F$4:$F$203,"Media") | H6: =COUNTIFS(Registro_Defectos!$C$4:$C$203,A6,Registro_Defectos!$F$4:$F$203,"Baja") | J6: =IF(OR(I6="",I6=0),"",ROUND((B6-I6)/I6*100,1)) | M6: =IF(OR(K6="",K6=0),"",ROUND(L6/K6*100,1))
A7: 3 | B7: =ROUND(SUMIFS(Bitacora_Tiempo!$H$4:$H$203,Bitacora_Tiempo!$B$4:$B$203,A7)/60,2) | C7: =COUNTIFS(Registro_Defectos!$C$4:$C$203,A7,Registro_Defectos!$A$4:$A$203,"<>") | D7: =IF(B7=0,"",ROUND(C7/B7,2)) | E7: =COUNTIFS(Registro_Defectos!$C$4:$C$203,A7,Registro_Defectos!$F$4:$F$203,"Bloqueante") | F7: =COUNTIFS(Registro_Defectos!$C$4:$C$203,A7,Registro_Defectos!$F$4:$F$203,"Alta") | G7: =COUNTIFS(Registro_Defectos!$C$4:$C$203,A7,Registro_Defectos!$F$4:$F$203,"Media") | H7: =COUNTIFS(Registro_Defectos!$C$4:$C$203,A7,Registro_Defectos!$F$4:$F$203,"Baja") | J7: =IF(OR(I7="",I7=0),"",ROUND((B7-I7)/I7*100,1)) | M7: =IF(OR(K7="",K7=0),"",ROUND(L7/K7*100,1))
A8: 4 | B8: =ROUND(SUMIFS(Bitacora_Tiempo!$H$4:$H$203,Bitacora_Tiempo!$B$4:$B$203,A8)/60,2) | C8: =COUNTIFS(Registro_Defectos!$C$4:$C$203,A8,Registro_Defectos!$A$4:$A$203,"<>") | D8: =IF(B8=0,"",ROUND(C8/B8,2)) | E8: =COUNTIFS(Registro_Defectos!$C$4:$C$203,A8,Registro_Defectos!$F$4:$F$203,"Bloqueante") | F8: =COUNTIFS(Registro_Defectos!$C$4:$C$203,A8,Registro_Defectos!$F$4:$F$203,"Alta") | G8: =COUNTIFS(Registro_Defectos!$C$4:$C$203,A8,Registro_Defectos!$F$4:$F$203,"Media") | H8: =COUNTIFS(Registro_Defectos!$C$4:$C$203,A8,Registro_Defectos!$F$4:$F$203,"Baja") | J8: =IF(OR(I8="",I8=0),"",ROUND((B8-I8)/I8*100,1)) | M8: =IF(OR(K8="",K8=0),"",ROUND(L8/K8*100,1))
A10: Tasa de defectos por integrante (M-20)
A11: Sprint | B11: Integrante | C11: Horas netas | D11: Defectos que introdujo | E11: Defectos por hora
A12: 1 | B12: Mikael Ramos | C12: =ROUND(SUMIFS(Bitacora_Tiempo!$H$4:$H$203,Bitacora_Tiempo!$B$4:$B$203,A12,Bitacora_Tiempo!$C$4:$C$203,B12,Bitacora_Tiempo!$D$4:$D$203,"Código")/60+SUMIFS(Bitacora_Tiempo!$H$4:$H$203,Bitacora_Tiempo!$B$4:$B$203,A12,Bitacora_Tiempo!$C$4:$C$203,B12,Bitacora_Tiempo!$D$4:$D$203,"Diseño")/60,2) | D12: =COUNTIFS(Registro_Defectos!$C$4:$C$203,A12,Registro_Defectos!$K$4:$K$203,B12) | E12: =IF(C12=0,"",ROUND(D12/C12,2))
A13: 1 | B13: Kevin Zambrano | C13: =ROUND(SUMIFS(Bitacora_Tiempo!$H$4:$H$203,Bitacora_Tiempo!$B$4:$B$203,A13,Bitacora_Tiempo!$C$4:$C$203,B13,Bitacora_Tiempo!$D$4:$D$203,"Código")/60+SUMIFS(Bitacora_Tiempo!$H$4:$H$203,Bitacora_Tiempo!$B$4:$B$203,A13,Bitacora_Tiempo!$C$4:$C$203,B13,Bitacora_Tiempo!$D$4:$D$203,"Diseño")/60,2) | D13: =COUNTIFS(Registro_Defectos!$C$4:$C$203,A13,Registro_Defectos!$K$4:$K$203,B13) | E13: =IF(C13=0,"",ROUND(D13/C13,2))
A14: 2 | B14: Mikael Ramos | C14: =ROUND(SUMIFS(Bitacora_Tiempo!$H$4:$H$203,Bitacora_Tiempo!$B$4:$B$203,A14,Bitacora_Tiempo!$C$4:$C$203,B14,Bitacora_Tiempo!$D$4:$D$203,"Código")/60+SUMIFS(Bitacora_Tiempo!$H$4:$H$203,Bitacora_Tiempo!$B$4:$B$203,A14,Bitacora_Tiempo!$C$4:$C$203,B14,Bitacora_Tiempo!$D$4:$D$203,"Diseño")/60,2) | D14: =COUNTIFS(Registro_Defectos!$C$4:$C$203,A14,Registro_Defectos!$K$4:$K$203,B14) | E14: =IF(C14=0,"",ROUND(D14/C14,2))
A15: 2 | B15: Kevin Zambrano | C15: =ROUND(SUMIFS(Bitacora_Tiempo!$H$4:$H$203,Bitacora_Tiempo!$B$4:$B$203,A15,Bitacora_Tiempo!$C$4:$C$203,B15,Bitacora_Tiempo!$D$4:$D$203,"Código")/60+SUMIFS(Bitacora_Tiempo!$H$4:$H$203,Bitacora_Tiempo!$B$4:$B$203,A15,Bitacora_Tiempo!$C$4:$C$203,B15,Bitacora_Tiempo!$D$4:$D$203,"Diseño")/60,2) | D15: =COUNTIFS(Registro_Defectos!$C$4:$C$203,A15,Registro_Defectos!$K$4:$K$203,B15) | E15: =IF(C15=0,"",ROUND(D15/C15,2))
A16: 3 | B16: Mikael Ramos | C16: =ROUND(SUMIFS(Bitacora_Tiempo!$H$4:$H$203,Bitacora_Tiempo!$B$4:$B$203,A16,Bitacora_Tiempo!$C$4:$C$203,B16,Bitacora_Tiempo!$D$4:$D$203,"Código")/60+SUMIFS(Bitacora_Tiempo!$H$4:$H$203,Bitacora_Tiempo!$B$4:$B$203,A16,Bitacora_Tiempo!$C$4:$C$203,B16,Bitacora_Tiempo!$D$4:$D$203,"Diseño")/60,2) | D16: =COUNTIFS(Registro_Defectos!$C$4:$C$203,A16,Registro_Defectos!$K$4:$K$203,B16) | E16: =IF(C16=0,"",ROUND(D16/C16,2))
A17: 3 | B17: Kevin Zambrano | C17: =ROUND(SUMIFS(Bitacora_Tiempo!$H$4:$H$203,Bitacora_Tiempo!$B$4:$B$203,A17,Bitacora_Tiempo!$C$4:$C$203,B17,Bitacora_Tiempo!$D$4:$D$203,"Código")/60+SUMIFS(Bitacora_Tiempo!$H$4:$H$203,Bitacora_Tiempo!$B$4:$B$203,A17,Bitacora_Tiempo!$C$4:$C$203,B17,Bitacora_Tiempo!$D$4:$D$203,"Diseño")/60,2) | D17: =COUNTIFS(Registro_Defectos!$C$4:$C$203,A17,Registro_Defectos!$K$4:$K$203,B17) | E17: =IF(C17=0,"",ROUND(D17/C17,2))
A18: 4 | B18: Mikael Ramos | C18: =ROUND(SUMIFS(Bitacora_Tiempo!$H$4:$H$203,Bitacora_Tiempo!$B$4:$B$203,A18,Bitacora_Tiempo!$C$4:$C$203,B18,Bitacora_Tiempo!$D$4:$D$203,"Código")/60+SUMIFS(Bitacora_Tiempo!$H$4:$H$203,Bitacora_Tiempo!$B$4:$B$203,A18,Bitacora_Tiempo!$C$4:$C$203,B18,Bitacora_Tiempo!$D$4:$D$203,"Diseño")/60,2) | D18: =COUNTIFS(Registro_Defectos!$C$4:$C$203,A18,Registro_Defectos!$K$4:$K$203,B18) | E18: =IF(C18=0,"",ROUND(D18/C18,2))
A19: 4 | B19: Kevin Zambrano | C19: =ROUND(SUMIFS(Bitacora_Tiempo!$H$4:$H$203,Bitacora_Tiempo!$B$4:$B$203,A19,Bitacora_Tiempo!$C$4:$C$203,B19,Bitacora_Tiempo!$D$4:$D$203,"Código")/60+SUMIFS(Bitacora_Tiempo!$H$4:$H$203,Bitacora_Tiempo!$B$4:$B$203,A19,Bitacora_Tiempo!$C$4:$C$203,B19,Bitacora_Tiempo!$D$4:$D$203,"Diseño")/60,2) | D19: =COUNTIFS(Registro_Defectos!$C$4:$C$203,A19,Registro_Defectos!$K$4:$K$203,B19) | E19: =IF(C19=0,"",ROUND(D19/C19,2))

Sheet NPR
A1: Número de Prioridad de Riesgo = Gravedad × Ocurrencia × Detección (cada factor de 1 a 10). Con 100 o más se exige revisión de código por el otro integrante.
A3: Función | B3: Falla posible | C3: Gravedad | D3: Ocurrencia | E3: Detección | F3: NPR | G3: Decisión
A4: iniciar_sesion | B4: Acceso indebido o bloqueo que no se aplica | C4: 9 | D4: 4 | E4: 4 | F4: =C4*D4*E4 | G4: =IF(F4>=100,"Revisión de código por el otro integrante y prueba de seguridad","Revisión normal")
A5: calcular_utilidad | B5: Utilidad o rentabilidad con un valor erróneo | C5: 8 | D5: 3 | E5: 4 | F5: =C5*D5*E5 | G5: =IF(F5>=100,"Revisión de código por el otro integrante y prueba de seguridad","Revisión normal")
A6: verificar_codigo | B6: Cuenta activada con un código vencido o agotado | C6: 7 | D6: 4 | E6: 3 | F6: =C6*D6*E6 | G6: =IF(F6>=100,"Revisión de código por el otro integrante y prueba de seguridad","Revisión normal")
A7: matas_por_hectarea | B7: Cantidad de matas distinta a la real, con efecto en insumos y costos | C7: 8 | D7: 3 | E7: 3 | F7: =C7*D7*E7 | G7: =IF(F7>=100,"Revisión de código por el otro integrante y prueba de seguridad","Revisión normal")
